sudoroll/__init__.py
sudoroll/curses.txt
sudoroll/main.py
sudoroll-1.0.0.dist-info/METADATA
sudoroll-1.0.0.dist-info/WHEEL
sudoroll-1.0.0.dist-info/entry_points.txt
sudoroll-1.0.0.dist-info/top_level.txt
sudoroll-1.0.0.dist-info/RECORD
