Metadata-Version: 2.4
Name: sudoroll
Version: 1.0.0
Summary: A simple, slightly mean command-line dice roller.
Author-email: laulowcode <enigma15012001@gmail.com>
Classifier: Programming Language :: Python :: 3
Classifier: License :: OSI Approved :: MIT License
Classifier: Operating System :: OS Independent
Requires-Python: >=3.7
Requires-Dist: importlib_resources; python_version < "3.9"
